{
  "symfony/asset": "<6.0 || > 6.0.9999",
  "symfony/browser-kit": "<6.0 || > 6.0.9999",
  "symfony/cache": "<6.0 || > 6.0.9999",
  "symfony/config": "<6.0 || > 6.0.9999",
  "symfony/console": "<6.0 || > 6.0.9999",
  "symfony/css-selector": "<6.0 || > 6.0.9999",
  "symfony/dependency-injection": "<6.0 || > 6.0.9999",
  "symfony/debug-bundle": "<6.0 || > 6.0.9999",
  "symfony/doctrine-bridge": "<6.0 || > 6.0.9999",
  "symfony/dom-crawler": "<6.0 || > 6.0.9999",
  "symfony/dotenv": "<6.0 || > 6.0.9999",
  "symfony/error-handler": "<6.0 || > 6.0.9999",
  "symfony/event-dispatcher": "<6.0 || > 6.0.9999",
  "symfony/expression-language": "<6.0 || > 6.0.9999",
  "symfony/filesystem": "<6.0 || > 6.0.9999",
  "symfony/finder": "<6.0 || > 6.0.9999",
  "symfony/form": "<6.0 || > 6.0.9999",
  "symfony/framework-bundle": "<6.0 || > 6.0.9999",
  "symfony/http-client": "<6.0 || > 6.0.9999",
  "symfony/http-foundation": "<6.0 || > 6.0.9999",
  "symfony/http-kernel": "<6.0 || > 6.0.9999",
  "symfony/intl": "<6.0 || > 6.0.9999",
  "symfony/ldap": "<6.0 || > 6.0.9999",
  "symfony/lock": "<6.0 || > 6.0.9999",
  "symfony/mailer": "<6.0 || > 6.0.9999",
  "symfony/messenger": "<6.0 || > 6.0.9999",
  "symfony/mime": "<6.0 || > 6.0.9999",
  "symfony/monolog-bridge": "<6.0 || > 6.0.9999",
  "symfony/notifier": "<6.0 || > 6.0.9999",
  "symfony/options-resolver": "<6.0 || > 6.0.9999",
  "symfony/password-hasher": "<6.0 || > 6.0.9999",
  "symfony/process": "<6.0 || > 6.0.9999",
  "symfony/property-access": "<6.0 || > 6.0.9999",
  "symfony/property-info": "<6.0 || > 6.0.9999",
  "symfony/proxy-manager-bridge": "<6.0 || > 6.0.9999",
  "symfony/rate-limiter": "<6.0 || > 6.0.9999",
  "symfony/routing": "<6.0 || > 6.0.9999",
  "symfony/security-bundle": "<6.0 || > 6.0.9999",
  "symfony/security-core": "<6.0 || > 6.0.9999",
  "symfony/security-csrf": "<6.0 || > 6.0.9999",
  "symfony/security-guard": "<6.0 || > 6.0.9999",
  "symfony/security-http": "<6.0 || > 6.0.9999",
  "symfony/semaphore": "<6.0 || > 6.0.9999",
  "symfony/serializer": "<6.0 || > 6.0.9999",
  "symfony/stopwatch": "<6.0 || > 6.0.9999",
  "symfony/string": "<6.0 || > 6.0.9999",
  "symfony/templating": "<6.0 || > 6.0.9999",
  "symfony/translation": "<6.0 || > 6.0.9999",
  "symfony/twig-bridge": "<6.0 || > 6.0.9999",
  "symfony/twig-bundle": "<6.0 || > 6.0.9999",
  "symfony/uid": "<6.0 || > 6.0.9999",
  "symfony/validator": "<6.0 || > 6.0.9999",
  "symfony/var-dumper": "<6.0 || > 6.0.9999",
  "symfony/var-exporter": "<6.0 || > 6.0.9999",
  "symfony/web-link": "<6.0 || > 6.0.9999",
  "symfony/web-profiler-bundle": "<6.0 || > 6.0.9999",
  "symfony/workflow": "<6.0 || > 6.0.9999",
  "symfony/yaml": "<6.0 || > 6.0.9999"
}
